{"title":"Body","body":{"content":{"application/x-www-form-urlencoded":{"schema":{"type":"object","required":["node_id","title","message"],"properties":{"node_id":{"type":"integer","description":"ID of the forum to create the thread in."},"title":{"type":"string","description":"Title of the thread."},"message":{"type":"string","description":"Body of the first post in the thread."},"discussion_type":{"type":"string","description":"The type of thread to create. Specific types may require additional input."},"prefix_id":{"type":"integer","description":"ID of the prefix to apply to the thread. If not valid in the selected forum, will be ignored."},"tags":{"type":"array","items":{"type":"string"},"description":"Array of tag names to apply to the thread."},"custom_fields[<name>]":{"type":"string","description":"Value to apply to the custom field with the specified name."},"discussion_open":{"type":"boolean"},"sticky":{"type":"boolean"},"attachment_key":{"type":"string","description":"API attachment key to upload files. Attachment key context type must be post with context[node_id] set to the ID of the forum this is being posted in."}}}}},"required":true}}