{"title":"Body","body":{"content":{"application/x-www-form-urlencoded":{"schema":{"type":"object","required":["client_id","grant_type"],"properties":{"client_id":{"type":"string"},"client_secret":{"type":"string","description":"Required for confidential clients."},"grant_type":{"type":"string","description":"Either 'authorization_code' or 'refresh_token'."},"code":{"type":"string","description":"Required when grant_type is 'authorization_code'."},"refresh_token":{"type":"string","description":"Required when grant_type is 'refresh_token'."},"code_verifier":{"type":"string","description":"Required for public clients using PKCE with 'authorization_code' grant."},"redirect_uri":{"type":"string","description":"Required when grant_type is 'authorization_code'."}}}}},"required":true}}