{"title":"Body","body":{"content":{"application/x-www-form-urlencoded":{"schema":{"type":"object","properties":{"message":{"type":"string"},"silent":{"type":"boolean","description":"If true and permissions allow, this edit will not be updated with a \"last edited\" indication"},"clear_edit":{"type":"boolean","description":"If true and permissions allow, any \"last edited\" indication will be removed. Requires \"silent\"."},"author_alert":{"type":"boolean"},"author_alert_reason":{"type":"string"}}}}}}}